jsonqfy/__init__.py
jsonqfy/jsonfy.py
jsonqfy/utils/__init__.py
jsonqfy/utils/parses.py
jsonqfy-0.1.1.5.dist-info/METADATA
jsonqfy-0.1.1.5.dist-info/WHEEL
jsonqfy-0.1.1.5.dist-info/top_level.txt
jsonqfy-0.1.1.5.dist-info/RECORD
