Metadata-Version: 2.1
Name: jsonqfy
Version: 0.1.1.5
Author: BecomeAllan
Author-email: becomeallan@gmail.com
Provides-Extra: parse
Requires-Dist: pandoc ; extra == 'parse'
Requires-Dist: beautifulsoup4 ; extra == 'parse'
